[
  {
    "name": "Sekhar, Fang of Nulahmia",
    "regimentOptions": "Any <Vampire Lord>",
    "replace": false
  },
  {
    "name": "Vampire Lord",
    "regimentOptions": "Any <Vampire Lord>",
    "replace": false
  },
  {
    "name": "Coven Throne",
    "regimentOptions": "Any <Vampire Lord>",
    "replace": false
  },
  {
    "name": "Bloodseeker Palanquin",
    "regimentOptions": "Any <Vampire Lord>",
    "replace": false
  },
  {
    "name": "Sekhar, Fang of Nulahmia (Scourge of Ghyran)",
    "regimentOptions": "Any <Vampire Lord>",
    "replace": false
  }
]